Metadata-Version: 2.1
Name: django-array-field-select-multiple
Version: 0.3.0
Summary: A replacement for Django's ArrayField with a multiple select form field.
Home-page: https://github.com/Waszker/django-array-field-select
Author: Piotr Waszkiewicz
Author-email: waszka23@gmail.com
License: MIT
Classifier: Framework :: Django
Classifier: Programming Language :: Python :: 3
License-File: LICENSE
